{
    "@context": "https://iiif.dl.itc.u-tokyo.ac.jp/repo/api-context",
    "@id": "https://iiif.dl.itc.u-tokyo.ac.jp/repo/api/items/220425",
    "@type": "o:Item",
    "bibo:identifier": [
        {
            "@value": "64346f2f-29fd-43ca-af0b-01c5adc38364",
            "is_public": true,
            "property_id": 98,
            "property_label": "identifier",
            "type": "literal"
        }
    ],
    "dcterms:isPartOf": [
        {
            "@id": "https://iiif.dl.itc.u-tokyo.ac.jp/repo/s/piranesi/",
            "is_public": true,
            "property_id": 33,
            "property_label": "Is Part Of",
            "type": "uri"
        }
    ],
    "dcterms:relation": [
        {
            "@id": "https://iiif.dl.itc.u-tokyo.ac.jp/repo/s/piranesi/document/64346f2f-29fd-43ca-af0b-01c5adc38364",
            "is_public": true,
            "property_id": 13,
            "property_label": "Relation",
            "type": "uri"
        }
    ],
    "dcterms:rights": [
        {
            "@id": "https://www.lib.u-tokyo.ac.jp/ja/library/contents/archives-top/reuse",
            "is_public": true,
            "o:label": "https://www.lib.u-tokyo.ac.jp/ja/library/contents/archives-top/reuse",
            "property_id": 15,
            "property_label": "Rights",
            "type": "uri"
        }
    ],
    "dcterms:title": [
        {
            "@value": "Grande pianta topografica del Campo Marzio, in sei tavole di cm. 59 x 45 da riunirsi (135 x 117). La tav. 5 porta sopra una ricca lapide di marmo la scritta in rilievo: Roberto Adam Britanno Architecturae Cultori Ichnographiam Campi Martii Antiquae Urbis Joannes Baptista Piranesius in Sui Amoris Argumentum D. D. D.",
            "is_public": true,
            "property_id": 1,
            "property_label": "Title",
            "type": "literal"
        }
    ],
    "foaf:thumbnail": [
        {
            "@id": "https://iiif.dl.itc.u-tokyo.ac.jp/repo/files/medium/41756b075f5e871f4ba101d2d19fe1f0afcb3fed.jpg",
            "is_public": true,
            "property_id": 157,
            "property_label": "thumbnail",
            "type": "uri"
        }
    ],
    "o:created": {
        "@type": "http://www.w3.org/2001/XMLSchema#dateTime",
        "@value": "2019-01-21T16:14:36+00:00"
    },
    "o:id": 220425,
    "o:is_public": true,
    "o:item_set": [
        {
            "@id": "https://iiif.dl.itc.u-tokyo.ac.jp/repo/api/item_sets/219908",
            "o:id": 219908
        }
    ],
    "o:media": [
        {
            "@id": "https://iiif.dl.itc.u-tokyo.ac.jp/repo/api/media/221865",
            "o:id": 221865
        }
    ],
    "o:modified": {
        "@type": "http://www.w3.org/2001/XMLSchema#dateTime",
        "@value": "2020-07-17T02:10:41+00:00"
    },
    "o:owner": {
        "@id": "https://iiif.dl.itc.u-tokyo.ac.jp/repo/api/users/1",
        "o:id": 1
    },
    "o:resource_class": null,
    "o:resource_template": {
        "@id": "https://iiif.dl.itc.u-tokyo.ac.jp/repo/api/resource_templates/20",
        "o:id": 20
    },
    "o:thumbnail": null,
    "pi:author": [
        {
            "@value": "Giovanni Battista Piranesi",
            "is_public": true,
            "property_id": 404,
            "property_label": "author",
            "type": "literal"
        }
    ],
    "pi:author_jp": [
        {
            "@value": "ジョヴァンニ・バッティスタ・ピラネージ",
            "is_public": true,
            "property_id": 405,
            "property_label": "author_JP",
            "type": "literal"
        }
    ],
    "pi:calco_no": [
        {
            "@value": "425",
            "is_public": true,
            "property_id": 406,
            "property_label": "Calco_no",
            "type": "literal"
        }
    ],
    "pi:calco_tav_no": [
        {
            "@value": "tav. 5",
            "is_public": true,
            "property_id": 407,
            "property_label": "Calco_tav_no",
            "type": "literal"
        }
    ],
    "pi:fd_no": [
        {
            "@value": "425",
            "is_public": true,
            "property_id": 414,
            "property_label": "FD_no",
            "type": "literal"
        }
    ],
    "pi:hf_desc": [
        {
            "@value": "440. V. Plan de grandes dimensions, en six parties. -- En haut à gauche, sur une pierre décorée d'une riche bordure, troisième dédicace à Robert Adam : ROBERTO ADAM BRITANNO ARCHITECTURAE CULTORI ICHNOGRAPHIAM CAMPI MARTII ANTIQUAE URBIS JOANNES-BAPTISTA PIRANESI IN SUI AMORIS ARGUMENTUM D.D.D. -- S. sig. -- H. 1.35. L. 1.17. -- Fil d'encad. aut. du plan.",
            "is_public": true,
            "property_id": 416,
            "property_label": "HF_desc",
            "type": "literal"
        }
    ],
    "pi:hf_desc_tr": [
        {
            "@value": "440。図版5。6つの部分からなる大きな寸法の地図。−左上部,豪華な縁どり装飾が施された石碑に,ロバート・アダムへの第3の献辞〔が以下のように記されている〕。「親愛なる英国人建築家,ロバート・アダムへ,古代都市のカンプス・マルティウスの平面図,ジョヴァンニ・バッティスタ・ピラネージ,敬愛の印に捧ぐ」 −署名なし。−高さ1.35,長さ1.17。−地図の周囲に枠線。",
            "is_public": true,
            "property_id": 417,
            "property_label": "HF_desc_tr",
            "type": "literal"
        }
    ],
    "pi:hf_no": [
        {
            "@value": "440",
            "is_public": true,
            "property_id": 418,
            "property_label": "HF_no",
            "type": "literal"
        }
    ],
    "pi:image_id": [
        {
            "@value": "518",
            "is_public": true,
            "property_id": 424,
            "property_label": "image_ID",
            "type": "literal"
        }
    ],
    "pi:image_size": [
        {
            "@value": "449X585",
            "is_public": true,
            "property_id": 425,
            "property_label": "image_size",
            "type": "literal"
        }
    ],
    "pi:inscription1": [
        {
            "@value": "ROBERTO. ADAM. BRITANNOARCHITECTVRAE. CVLTORIICHNOGRAPHIAMCAMPI. MARTIIANTIQUAE. VRBISIOANNES. BAPTISTA. PIRANESIUSIN. SUI. AMORIS. ARGVMENTVMD. D. D.TOPOGRAPHIA ROMAELONGITVUDINEM CAMPIMARTII ADVUSQUE PONTEMMILVIVM DEMONSTRANS",
            "is_public": true,
            "property_id": 427,
            "property_label": "inscription1",
            "type": "literal"
        }
    ],
    "pi:inscription1_tr": [
        {
            "@value": "英国人建築家,ロバート・アダム1へ古代都市ローマのカンプス・マルティウスの平面図をジョヴァンニ・バッティスタ・ピラネージが,敬愛の印に捧ぐ",
            "is_public": true,
            "property_id": 428,
            "property_label": "inscription1_tr",
            "type": "literal"
        }
    ],
    "pi:inscription2_tr": [
        {
            "@value": "カンプス・マルティウスのムルウィウス橋1[モッレ橋]にいたるまでの区間を示すローマの地勢図",
            "is_public": true,
            "property_id": 430,
            "property_label": "inscription2_tr",
            "type": "literal"
        }
    ],
    "pi:kamei_no": [
        {
            "@value": "425",
            "is_public": true,
            "property_id": 431,
            "property_label": "Kamei_no",
            "type": "literal"
        }
    ],
    "pi:kanagawa_no": [
        {
            "@value": "93a",
            "is_public": true,
            "property_id": 432,
            "property_label": "Kanagawa_no",
            "type": "literal"
        }
    ],
    "pi:memo": [
        {
            "@value": "亀井文庫番号425-430の6枚組の版画。",
            "is_public": true,
            "property_id": 438,
            "property_label": "memo",
            "type": "literal"
        }
    ],
    "pi:nega_no": [
        {
            "@value": "10008",
            "is_public": true,
            "property_id": 439,
            "property_label": "nega_no",
            "type": "literal"
        }
    ],
    "pi:plate": [
        {
            "@value": "8",
            "is_public": true,
            "property_id": 445,
            "property_label": "plate",
            "type": "literal"
        }
    ],
    "pi:plate_size": [
        {
            "@value": "455X597",
            "is_public": true,
            "property_id": 446,
            "property_label": "plate_size",
            "type": "literal"
        }
    ],
    "pi:series": [
        {
            "@value": "IL CAMPO MARZIO  DELL' ANTICA ROMA",
            "is_public": true,
            "property_id": 448,
            "property_label": "series",
            "type": "literal"
        }
    ],
    "pi:series_jp": [
        {
            "@value": "古代ローマのカンプス・マルティウス",
            "is_public": true,
            "property_id": 449,
            "property_label": "series_JP",
            "type": "literal"
        }
    ],
    "pi:subject": [
        {
            "@value": "maps",
            "is_public": true,
            "property_id": 471,
            "property_label": "subject",
            "type": "literal"
        }
    ],
    "pi:taschen_no": [
        {
            "@value": "493",
            "is_public": true,
            "property_id": 452,
            "property_label": "Taschen_no",
            "type": "literal"
        }
    ],
    "pi:tav_no": [
        {
            "@value": "Tab.V",
            "is_public": true,
            "property_id": 453,
            "property_label": "tav_no",
            "type": "literal"
        }
    ],
    "pi:title": [
        {
            "@value": "Grande pianta topografica del Campo Marzio, in sei tavole di cm. 59 x 45 da riunirsi (135 x 117). La tav. 5 porta sopra una ricca lapide di marmo la scritta in rilievo: Roberto Adam Britanno Architecturae Cultori Ichnographiam Campi Martii Antiquae Urbis Joannes Baptista Piranesius in Sui Amoris Argumentum D. D. D.",
            "is_public": true,
            "property_id": 456,
            "property_label": "title",
            "type": "literal"
        }
    ],
    "pi:title_jp": [
        {
            "@value": "カンプス・マルティウスの大地図",
            "is_public": true,
            "property_id": 458,
            "property_label": "title_JP",
            "type": "literal"
        }
    ],
    "pi:tomo": [
        {
            "@value": "DECIMO",
            "is_public": true,
            "property_id": 459,
            "property_label": "tomo",
            "type": "literal"
        }
    ],
    "pi:tr_comment1": [
        {
            "@value": "ロバート・アダムRobert Adam(1728年-1792年)は,スコットランド出身の建築家兼デザイナーで,イギリスにおける新古典主義の指導者の1人である。同じく建築家である,兄弟達とも共同制作し,カントリー・ハウス,公共建築,都市開発,室内装飾などに携わった。1754年-1757年にかけて,グランド・ツアーとしてイタリアを巡り,1755年-1757年にはローマに滞在し,その際にピラネージと友好関係を結び,その友情は長く続いた。アダムは,ピラネージの『古代ローマのカンプス・マルティウス』の出版の際に出資者となり,ピラネージはアダムにそれを献呈している。アダムの言葉によれば,ピラネージは「かつて出会った中で最も驚異的な人物」であり,同時代では「古代の空気を吸う」唯一のイタリア人であった。考古学的見地からは,『スパラトのディオクレティアヌス帝の宮殿遺構』Ruins of the Palace of the Emperor Diocletian at Spalatro in Dalmatia(1764年)を刊行している。弟ジェームズと共著の『建築作品集』Works in Architecture(1773年以降刊行)は,アダムの影響を広範囲に広めたが,この作品集のためにピラネージは,版画家の1人として名を連ね,1778年に4つの版を制作した。",
            "is_public": true,
            "property_id": 460,
            "property_label": "tr_comment1",
            "type": "literal"
        }
    ],
    "pi:tr_comment2": [
        {
            "@value": "ムルウィウス橋は,前3世紀に木造の橋として架けられており,前2世紀にケンソル(検閲官)のマルクス・アエミリウス・スカウルスによリ凝灰岩で再建され,15世紀に教皇ニコラウス5世により監視塔が付加された。そして教皇ピウス7世により,ヴァラディエの設計(1805年)に基づき,城門型に姿を変えられた。この橋を有名にしたのは,312年10月28日にこの付近で行われた有名なコンスタンティヌス帝とマクセンティウス帝の戦いのためである。最終的にキリストの徴に導かれたと伝えられるコンスタンティヌス帝が勝利し,その後のキリスト教を国教とするローマ帝国の歴史のきっかけとなった戦いである。",
            "is_public": true,
            "property_id": 461,
            "property_label": "tr_comment2",
            "type": "literal"
        }
    ],
    "pi:volume": [
        {
            "@value": "10",
            "is_public": true,
            "property_id": 462,
            "property_label": "volume",
            "type": "literal"
        }
    ],
    "pi:we_desc": [
        {
            "@value": "Giant plan in six continuous plates dedicated to Robert Adam, dated 1757. Fold-out plate. Cf. 571 A-F, in appendix.Unsigned.",
            "is_public": true,
            "property_id": 463,
            "property_label": "WE_desc",
            "type": "literal"
        }
    ],
    "pi:we_no": [
        {
            "@value": "571",
            "is_public": true,
            "property_id": 464,
            "property_label": "WE_no",
            "type": "literal"
        }
    ],
    "pi:we_title": [
        {
            "@value": "\"Ichnographia\" or plan of the Campus Martius of the ancient city.",
            "is_public": true,
            "property_id": 465,
            "property_label": "WE_title",
            "type": "literal"
        }
    ],
    "rdfs:seeAlso": [
        {
            "@id": "https://iiif.dl.itc.u-tokyo.ac.jp/repo/api/items/220425",
            "is_public": true,
            "property_id": 282,
            "property_label": "seeAlso",
            "type": "uri"
        }
    ],
    "sc:attributionLabel": [
        {
            "@value": "東京大学総合図書館 General Library, The University of Tokyo, JAPAN",
            "is_public": true,
            "property_id": 190,
            "property_label": "attributionLabel",
            "type": "literal"
        }
    ],
    "uterms:databaseLabel": [
        {
            "@value": "ピラネージ画像データベース Opere di Giovanni Battista Piranesi",
            "is_public": true,
            "property_id": 354,
            "property_label": "Database Label",
            "type": "literal"
        }
    ],
    "uterms:manifestUri": [
        {
            "@id": "https://iiif.dl.itc.u-tokyo.ac.jp/repo/iiif/64346f2f-29fd-43ca-af0b-01c5adc38364/manifest",
            "is_public": true,
            "property_id": 353,
            "property_label": "Manifest Uri",
            "type": "uri"
        }
    ],
    "uterms:sort": [
        {
            "@value": "0518",
            "is_public": true,
            "property_id": 352,
            "property_label": "Sort",
            "type": "literal"
        }
    ]
}