{
    "@context": "https://iiif.dl.itc.u-tokyo.ac.jp/repo/api-context",
    "@id": "https://iiif.dl.itc.u-tokyo.ac.jp/repo/api/items/25229",
    "@type": [
        "o:Item",
        "dctype:Image"
    ],
    "archiveshub:note": [
        {
            "@value": "従前ヨリ貯フ所ヲ一時ニ整理シテ貼附スル四冊ノ一別ニ大冊一アリ 四四、八、一二 成",
            "is_public": true,
            "property_id": 332,
            "property_label": "Note",
            "type": "literal"
        }
    ],
    "bibo:identifier": [
        {
            "@value": "2d522f09-a944-4348-afcc-69cf87e9dae4",
            "is_public": true,
            "property_id": 98,
            "property_label": "identifier",
            "type": "literal"
        }
    ],
    "dcndl:callNumber": [
        {
            "@value": "A00:6010",
            "is_public": true,
            "property_id": 239,
            "property_label": "Call Number",
            "type": "literal"
        }
    ],
    "dcndl:titleTranscription": [
        {
            "@value": "クンシュウジョウ (テイ)38",
            "is_public": true,
            "property_id": 246,
            "property_label": "Title Transcription",
            "type": "literal"
        }
    ],
    "dcndl:volume": [
        {
            "@value": "第39冊",
            "is_public": true,
            "property_id": 206,
            "property_label": "Volume",
            "type": "literal"
        }
    ],
    "dcterms:creator": [
        {
            "@value": "田中芳男",
            "is_public": true,
            "property_id": 2,
            "property_label": "Creator",
            "type": "literal"
        }
    ],
    "dcterms:extent": [
        {
            "@value": "214",
            "is_public": true,
            "property_id": 25,
            "property_label": "Extent",
            "type": "literal"
        }
    ],
    "dcterms:isPartOf": [
        {
            "@id": "https://iiif.dl.itc.u-tokyo.ac.jp/repo/s/tanaka",
            "is_public": true,
            "property_id": 33,
            "property_label": "Is Part Of",
            "type": "uri"
        }
    ],
    "dcterms:relation": [
        {
            "@id": "https://iiif.dl.itc.u-tokyo.ac.jp/repo/s/tanaka/document/2d522f09-a944-4348-afcc-69cf87e9dae4",
            "is_public": true,
            "property_id": 13,
            "property_label": "Relation",
            "type": "uri"
        }
    ],
    "dcterms:rights": [
        {
            "@id": "https://www.lib.u-tokyo.ac.jp/ja/library/contents/archives-top/reuse",
            "is_public": true,
            "o:label": "https://www.lib.u-tokyo.ac.jp/ja/library/contents/archives-top/reuse",
            "property_id": 15,
            "property_label": "Rights",
            "type": "uri"
        }
    ],
    "dcterms:title": [
        {
            "@value": "捃拾帖 (丁)三十八",
            "is_public": true,
            "property_id": 1,
            "property_label": "Title",
            "type": "literal"
        }
    ],
    "foaf:thumbnail": [
        {
            "@id": "https://iiif.dl.itc.u-tokyo.ac.jp/repo/files/medium/cb76d30385add9e30be2d70b08fe4b7647cb5df4.jpg",
            "is_public": true,
            "property_id": 157,
            "property_label": "thumbnail",
            "type": "uri"
        }
    ],
    "o:created": {
        "@type": "http://www.w3.org/2001/XMLSchema#dateTime",
        "@value": "2018-06-08T14:30:20+00:00"
    },
    "o:id": 25229,
    "o:is_public": true,
    "o:item_set": [
        {
            "@id": "https://iiif.dl.itc.u-tokyo.ac.jp/repo/api/item_sets/25179",
            "o:id": 25179
        }
    ],
    "o:media": [
        {
            "@id": "https://iiif.dl.itc.u-tokyo.ac.jp/repo/api/media/158146",
            "o:id": 158146
        },
        {
            "@id": "https://iiif.dl.itc.u-tokyo.ac.jp/repo/api/media/158147",
            "o:id": 158147
        },
        {
            "@id": "https://iiif.dl.itc.u-tokyo.ac.jp/repo/api/media/158148",
            "o:id": 158148
        },
        {
            "@id": "https://iiif.dl.itc.u-tokyo.ac.jp/repo/api/media/158149",
            "o:id": 158149
        },
        {
            "@id": "https://iiif.dl.itc.u-tokyo.ac.jp/repo/api/media/158150",
            "o:id": 158150
        },
        {
            "@id": "https://iiif.dl.itc.u-tokyo.ac.jp/repo/api/media/158151",
            "o:id": 158151
        },
        {
            "@id": "https://iiif.dl.itc.u-tokyo.ac.jp/repo/api/media/158152",
            "o:id": 158152
        },
        {
            "@id": "https://iiif.dl.itc.u-tokyo.ac.jp/repo/api/media/158153",
            "o:id": 158153
        },
        {
            "@id": "https://iiif.dl.itc.u-tokyo.ac.jp/repo/api/media/158154",
            "o:id": 158154
        },
        {
            "@id": "https://iiif.dl.itc.u-tokyo.ac.jp/repo/api/media/158155",
            "o:id": 158155
        },
        {
            "@id": "https://iiif.dl.itc.u-tokyo.ac.jp/repo/api/media/158156",
            "o:id": 158156
        },
        {
            "@id": "https://iiif.dl.itc.u-tokyo.ac.jp/repo/api/media/158157",
            "o:id": 158157
        },
        {
            "@id": "https://iiif.dl.itc.u-tokyo.ac.jp/repo/api/media/158158",
            "o:id": 158158
        },
        {
            "@id": "https://iiif.dl.itc.u-tokyo.ac.jp/repo/api/media/158159",
            "o:id": 158159
        },
        {
            "@id": "https://iiif.dl.itc.u-tokyo.ac.jp/repo/api/media/158160",
            "o:id": 158160
        },
        {
            "@id": "https://iiif.dl.itc.u-tokyo.ac.jp/repo/api/media/158161",
            "o:id": 158161
        },
        {
            "@id": "https://iiif.dl.itc.u-tokyo.ac.jp/repo/api/media/158162",
            "o:id": 158162
        },
        {
            "@id": "https://iiif.dl.itc.u-tokyo.ac.jp/repo/api/media/158163",
            "o:id": 158163
        },
        {
            "@id": "https://iiif.dl.itc.u-tokyo.ac.jp/repo/api/media/158164",
            "o:id": 158164
        },
        {
            "@id": "https://iiif.dl.itc.u-tokyo.ac.jp/repo/api/media/158165",
            "o:id": 158165
        },
        {
            "@id": "https://iiif.dl.itc.u-tokyo.ac.jp/repo/api/media/158166",
            "o:id": 158166
        },
        {
            "@id": "https://iiif.dl.itc.u-tokyo.ac.jp/repo/api/media/158167",
            "o:id": 158167
        },
        {
            "@id": "https://iiif.dl.itc.u-tokyo.ac.jp/repo/api/media/158168",
            "o:id": 158168
        },
        {
            "@id": "https://iiif.dl.itc.u-tokyo.ac.jp/repo/api/media/158169",
            "o:id": 158169
        },
        {
            "@id": "https://iiif.dl.itc.u-tokyo.ac.jp/repo/api/media/158170",
            "o:id": 158170
        },
        {
            "@id": "https://iiif.dl.itc.u-tokyo.ac.jp/repo/api/media/158171",
            "o:id": 158171
        },
        {
            "@id": "https://iiif.dl.itc.u-tokyo.ac.jp/repo/api/media/158172",
            "o:id": 158172
        },
        {
            "@id": "https://iiif.dl.itc.u-tokyo.ac.jp/repo/api/media/158173",
            "o:id": 158173
        },
        {
            "@id": "https://iiif.dl.itc.u-tokyo.ac.jp/repo/api/media/158174",
            "o:id": 158174
        },
        {
            "@id": "https://iiif.dl.itc.u-tokyo.ac.jp/repo/api/media/158175",
            "o:id": 158175
        },
        {
            "@id": "https://iiif.dl.itc.u-tokyo.ac.jp/repo/api/media/158176",
            "o:id": 158176
        },
        {
            "@id": "https://iiif.dl.itc.u-tokyo.ac.jp/repo/api/media/158177",
            "o:id": 158177
        },
        {
            "@id": "https://iiif.dl.itc.u-tokyo.ac.jp/repo/api/media/158178",
            "o:id": 158178
        },
        {
            "@id": "https://iiif.dl.itc.u-tokyo.ac.jp/repo/api/media/158179",
            "o:id": 158179
        },
        {
            "@id": "https://iiif.dl.itc.u-tokyo.ac.jp/repo/api/media/158180",
            "o:id": 158180
        },
        {
            "@id": "https://iiif.dl.itc.u-tokyo.ac.jp/repo/api/media/158181",
            "o:id": 158181
        },
        {
            "@id": "https://iiif.dl.itc.u-tokyo.ac.jp/repo/api/media/158182",
            "o:id": 158182
        },
        {
            "@id": "https://iiif.dl.itc.u-tokyo.ac.jp/repo/api/media/158183",
            "o:id": 158183
        },
        {
            "@id": "https://iiif.dl.itc.u-tokyo.ac.jp/repo/api/media/158184",
            "o:id": 158184
        },
        {
            "@id": "https://iiif.dl.itc.u-tokyo.ac.jp/repo/api/media/158185",
            "o:id": 158185
        },
        {
            "@id": "https://iiif.dl.itc.u-tokyo.ac.jp/repo/api/media/158186",
            "o:id": 158186
        },
        {
            "@id": "https://iiif.dl.itc.u-tokyo.ac.jp/repo/api/media/158187",
            "o:id": 158187
        },
        {
            "@id": "https://iiif.dl.itc.u-tokyo.ac.jp/repo/api/media/158188",
            "o:id": 158188
        },
        {
            "@id": "https://iiif.dl.itc.u-tokyo.ac.jp/repo/api/media/158189",
            "o:id": 158189
        },
        {
            "@id": "https://iiif.dl.itc.u-tokyo.ac.jp/repo/api/media/158190",
            "o:id": 158190
        },
        {
            "@id": "https://iiif.dl.itc.u-tokyo.ac.jp/repo/api/media/158191",
            "o:id": 158191
        },
        {
            "@id": "https://iiif.dl.itc.u-tokyo.ac.jp/repo/api/media/158192",
            "o:id": 158192
        },
        {
            "@id": "https://iiif.dl.itc.u-tokyo.ac.jp/repo/api/media/158193",
            "o:id": 158193
        },
        {
            "@id": "https://iiif.dl.itc.u-tokyo.ac.jp/repo/api/media/158194",
            "o:id": 158194
        },
        {
            "@id": "https://iiif.dl.itc.u-tokyo.ac.jp/repo/api/media/158195",
            "o:id": 158195
        },
        {
            "@id": "https://iiif.dl.itc.u-tokyo.ac.jp/repo/api/media/158196",
            "o:id": 158196
        },
        {
            "@id": "https://iiif.dl.itc.u-tokyo.ac.jp/repo/api/media/158197",
            "o:id": 158197
        },
        {
            "@id": "https://iiif.dl.itc.u-tokyo.ac.jp/repo/api/media/158198",
            "o:id": 158198
        },
        {
            "@id": "https://iiif.dl.itc.u-tokyo.ac.jp/repo/api/media/158199",
            "o:id": 158199
        },
        {
            "@id": "https://iiif.dl.itc.u-tokyo.ac.jp/repo/api/media/158200",
            "o:id": 158200
        },
        {
            "@id": "https://iiif.dl.itc.u-tokyo.ac.jp/repo/api/media/158201",
            "o:id": 158201
        },
        {
            "@id": "https://iiif.dl.itc.u-tokyo.ac.jp/repo/api/media/158202",
            "o:id": 158202
        },
        {
            "@id": "https://iiif.dl.itc.u-tokyo.ac.jp/repo/api/media/158203",
            "o:id": 158203
        },
        {
            "@id": "https://iiif.dl.itc.u-tokyo.ac.jp/repo/api/media/158204",
            "o:id": 158204
        },
        {
            "@id": "https://iiif.dl.itc.u-tokyo.ac.jp/repo/api/media/158205",
            "o:id": 158205
        },
        {
            "@id": "https://iiif.dl.itc.u-tokyo.ac.jp/repo/api/media/158206",
            "o:id": 158206
        },
        {
            "@id": "https://iiif.dl.itc.u-tokyo.ac.jp/repo/api/media/158207",
            "o:id": 158207
        },
        {
            "@id": "https://iiif.dl.itc.u-tokyo.ac.jp/repo/api/media/158208",
            "o:id": 158208
        },
        {
            "@id": "https://iiif.dl.itc.u-tokyo.ac.jp/repo/api/media/158209",
            "o:id": 158209
        },
        {
            "@id": "https://iiif.dl.itc.u-tokyo.ac.jp/repo/api/media/158210",
            "o:id": 158210
        },
        {
            "@id": "https://iiif.dl.itc.u-tokyo.ac.jp/repo/api/media/158211",
            "o:id": 158211
        },
        {
            "@id": "https://iiif.dl.itc.u-tokyo.ac.jp/repo/api/media/158212",
            "o:id": 158212
        },
        {
            "@id": "https://iiif.dl.itc.u-tokyo.ac.jp/repo/api/media/158213",
            "o:id": 158213
        },
        {
            "@id": "https://iiif.dl.itc.u-tokyo.ac.jp/repo/api/media/158214",
            "o:id": 158214
        },
        {
            "@id": "https://iiif.dl.itc.u-tokyo.ac.jp/repo/api/media/158215",
            "o:id": 158215
        },
        {
            "@id": "https://iiif.dl.itc.u-tokyo.ac.jp/repo/api/media/158216",
            "o:id": 158216
        },
        {
            "@id": "https://iiif.dl.itc.u-tokyo.ac.jp/repo/api/media/158217",
            "o:id": 158217
        },
        {
            "@id": "https://iiif.dl.itc.u-tokyo.ac.jp/repo/api/media/158218",
            "o:id": 158218
        },
        {
            "@id": "https://iiif.dl.itc.u-tokyo.ac.jp/repo/api/media/158219",
            "o:id": 158219
        },
        {
            "@id": "https://iiif.dl.itc.u-tokyo.ac.jp/repo/api/media/158220",
            "o:id": 158220
        },
        {
            "@id": "https://iiif.dl.itc.u-tokyo.ac.jp/repo/api/media/158221",
            "o:id": 158221
        },
        {
            "@id": "https://iiif.dl.itc.u-tokyo.ac.jp/repo/api/media/158222",
            "o:id": 158222
        },
        {
            "@id": "https://iiif.dl.itc.u-tokyo.ac.jp/repo/api/media/158223",
            "o:id": 158223
        },
        {
            "@id": "https://iiif.dl.itc.u-tokyo.ac.jp/repo/api/media/158224",
            "o:id": 158224
        },
        {
            "@id": "https://iiif.dl.itc.u-tokyo.ac.jp/repo/api/media/158225",
            "o:id": 158225
        },
        {
            "@id": "https://iiif.dl.itc.u-tokyo.ac.jp/repo/api/media/158226",
            "o:id": 158226
        },
        {
            "@id": "https://iiif.dl.itc.u-tokyo.ac.jp/repo/api/media/158227",
            "o:id": 158227
        },
        {
            "@id": "https://iiif.dl.itc.u-tokyo.ac.jp/repo/api/media/158228",
            "o:id": 158228
        },
        {
            "@id": "https://iiif.dl.itc.u-tokyo.ac.jp/repo/api/media/158229",
            "o:id": 158229
        },
        {
            "@id": "https://iiif.dl.itc.u-tokyo.ac.jp/repo/api/media/158230",
            "o:id": 158230
        },
        {
            "@id": "https://iiif.dl.itc.u-tokyo.ac.jp/repo/api/media/158231",
            "o:id": 158231
        },
        {
            "@id": "https://iiif.dl.itc.u-tokyo.ac.jp/repo/api/media/158232",
            "o:id": 158232
        },
        {
            "@id": "https://iiif.dl.itc.u-tokyo.ac.jp/repo/api/media/158233",
            "o:id": 158233
        },
        {
            "@id": "https://iiif.dl.itc.u-tokyo.ac.jp/repo/api/media/158234",
            "o:id": 158234
        },
        {
            "@id": "https://iiif.dl.itc.u-tokyo.ac.jp/repo/api/media/158235",
            "o:id": 158235
        },
        {
            "@id": "https://iiif.dl.itc.u-tokyo.ac.jp/repo/api/media/158236",
            "o:id": 158236
        },
        {
            "@id": "https://iiif.dl.itc.u-tokyo.ac.jp/repo/api/media/158237",
            "o:id": 158237
        },
        {
            "@id": "https://iiif.dl.itc.u-tokyo.ac.jp/repo/api/media/158238",
            "o:id": 158238
        },
        {
            "@id": "https://iiif.dl.itc.u-tokyo.ac.jp/repo/api/media/158239",
            "o:id": 158239
        },
        {
            "@id": "https://iiif.dl.itc.u-tokyo.ac.jp/repo/api/media/158240",
            "o:id": 158240
        },
        {
            "@id": "https://iiif.dl.itc.u-tokyo.ac.jp/repo/api/media/158241",
            "o:id": 158241
        },
        {
            "@id": "https://iiif.dl.itc.u-tokyo.ac.jp/repo/api/media/158242",
            "o:id": 158242
        },
        {
            "@id": "https://iiif.dl.itc.u-tokyo.ac.jp/repo/api/media/158243",
            "o:id": 158243
        },
        {
            "@id": "https://iiif.dl.itc.u-tokyo.ac.jp/repo/api/media/158244",
            "o:id": 158244
        },
        {
            "@id": "https://iiif.dl.itc.u-tokyo.ac.jp/repo/api/media/158245",
            "o:id": 158245
        },
        {
            "@id": "https://iiif.dl.itc.u-tokyo.ac.jp/repo/api/media/158246",
            "o:id": 158246
        },
        {
            "@id": "https://iiif.dl.itc.u-tokyo.ac.jp/repo/api/media/158247",
            "o:id": 158247
        },
        {
            "@id": "https://iiif.dl.itc.u-tokyo.ac.jp/repo/api/media/158248",
            "o:id": 158248
        },
        {
            "@id": "https://iiif.dl.itc.u-tokyo.ac.jp/repo/api/media/158249",
            "o:id": 158249
        },
        {
            "@id": "https://iiif.dl.itc.u-tokyo.ac.jp/repo/api/media/158250",
            "o:id": 158250
        },
        {
            "@id": "https://iiif.dl.itc.u-tokyo.ac.jp/repo/api/media/158251",
            "o:id": 158251
        },
        {
            "@id": "https://iiif.dl.itc.u-tokyo.ac.jp/repo/api/media/158252",
            "o:id": 158252
        },
        {
            "@id": "https://iiif.dl.itc.u-tokyo.ac.jp/repo/api/media/158253",
            "o:id": 158253
        },
        {
            "@id": "https://iiif.dl.itc.u-tokyo.ac.jp/repo/api/media/158254",
            "o:id": 158254
        },
        {
            "@id": "https://iiif.dl.itc.u-tokyo.ac.jp/repo/api/media/158255",
            "o:id": 158255
        },
        {
            "@id": "https://iiif.dl.itc.u-tokyo.ac.jp/repo/api/media/158256",
            "o:id": 158256
        },
        {
            "@id": "https://iiif.dl.itc.u-tokyo.ac.jp/repo/api/media/158257",
            "o:id": 158257
        },
        {
            "@id": "https://iiif.dl.itc.u-tokyo.ac.jp/repo/api/media/158258",
            "o:id": 158258
        },
        {
            "@id": "https://iiif.dl.itc.u-tokyo.ac.jp/repo/api/media/158259",
            "o:id": 158259
        },
        {
            "@id": "https://iiif.dl.itc.u-tokyo.ac.jp/repo/api/media/158260",
            "o:id": 158260
        },
        {
            "@id": "https://iiif.dl.itc.u-tokyo.ac.jp/repo/api/media/158261",
            "o:id": 158261
        },
        {
            "@id": "https://iiif.dl.itc.u-tokyo.ac.jp/repo/api/media/158262",
            "o:id": 158262
        },
        {
            "@id": "https://iiif.dl.itc.u-tokyo.ac.jp/repo/api/media/158263",
            "o:id": 158263
        },
        {
            "@id": "https://iiif.dl.itc.u-tokyo.ac.jp/repo/api/media/158264",
            "o:id": 158264
        },
        {
            "@id": "https://iiif.dl.itc.u-tokyo.ac.jp/repo/api/media/158265",
            "o:id": 158265
        },
        {
            "@id": "https://iiif.dl.itc.u-tokyo.ac.jp/repo/api/media/158266",
            "o:id": 158266
        },
        {
            "@id": "https://iiif.dl.itc.u-tokyo.ac.jp/repo/api/media/158267",
            "o:id": 158267
        },
        {
            "@id": "https://iiif.dl.itc.u-tokyo.ac.jp/repo/api/media/158268",
            "o:id": 158268
        },
        {
            "@id": "https://iiif.dl.itc.u-tokyo.ac.jp/repo/api/media/158269",
            "o:id": 158269
        },
        {
            "@id": "https://iiif.dl.itc.u-tokyo.ac.jp/repo/api/media/158270",
            "o:id": 158270
        },
        {
            "@id": "https://iiif.dl.itc.u-tokyo.ac.jp/repo/api/media/158271",
            "o:id": 158271
        },
        {
            "@id": "https://iiif.dl.itc.u-tokyo.ac.jp/repo/api/media/158272",
            "o:id": 158272
        },
        {
            "@id": "https://iiif.dl.itc.u-tokyo.ac.jp/repo/api/media/158273",
            "o:id": 158273
        },
        {
            "@id": "https://iiif.dl.itc.u-tokyo.ac.jp/repo/api/media/158274",
            "o:id": 158274
        },
        {
            "@id": "https://iiif.dl.itc.u-tokyo.ac.jp/repo/api/media/158275",
            "o:id": 158275
        },
        {
            "@id": "https://iiif.dl.itc.u-tokyo.ac.jp/repo/api/media/158276",
            "o:id": 158276
        },
        {
            "@id": "https://iiif.dl.itc.u-tokyo.ac.jp/repo/api/media/158277",
            "o:id": 158277
        },
        {
            "@id": "https://iiif.dl.itc.u-tokyo.ac.jp/repo/api/media/158278",
            "o:id": 158278
        },
        {
            "@id": "https://iiif.dl.itc.u-tokyo.ac.jp/repo/api/media/158279",
            "o:id": 158279
        },
        {
            "@id": "https://iiif.dl.itc.u-tokyo.ac.jp/repo/api/media/158280",
            "o:id": 158280
        },
        {
            "@id": "https://iiif.dl.itc.u-tokyo.ac.jp/repo/api/media/158281",
            "o:id": 158281
        },
        {
            "@id": "https://iiif.dl.itc.u-tokyo.ac.jp/repo/api/media/158282",
            "o:id": 158282
        },
        {
            "@id": "https://iiif.dl.itc.u-tokyo.ac.jp/repo/api/media/158283",
            "o:id": 158283
        },
        {
            "@id": "https://iiif.dl.itc.u-tokyo.ac.jp/repo/api/media/158284",
            "o:id": 158284
        },
        {
            "@id": "https://iiif.dl.itc.u-tokyo.ac.jp/repo/api/media/158285",
            "o:id": 158285
        },
        {
            "@id": "https://iiif.dl.itc.u-tokyo.ac.jp/repo/api/media/158286",
            "o:id": 158286
        },
        {
            "@id": "https://iiif.dl.itc.u-tokyo.ac.jp/repo/api/media/158287",
            "o:id": 158287
        },
        {
            "@id": "https://iiif.dl.itc.u-tokyo.ac.jp/repo/api/media/158288",
            "o:id": 158288
        },
        {
            "@id": "https://iiif.dl.itc.u-tokyo.ac.jp/repo/api/media/158289",
            "o:id": 158289
        },
        {
            "@id": "https://iiif.dl.itc.u-tokyo.ac.jp/repo/api/media/158290",
            "o:id": 158290
        },
        {
            "@id": "https://iiif.dl.itc.u-tokyo.ac.jp/repo/api/media/158291",
            "o:id": 158291
        },
        {
            "@id": "https://iiif.dl.itc.u-tokyo.ac.jp/repo/api/media/158292",
            "o:id": 158292
        },
        {
            "@id": "https://iiif.dl.itc.u-tokyo.ac.jp/repo/api/media/158293",
            "o:id": 158293
        },
        {
            "@id": "https://iiif.dl.itc.u-tokyo.ac.jp/repo/api/media/158294",
            "o:id": 158294
        },
        {
            "@id": "https://iiif.dl.itc.u-tokyo.ac.jp/repo/api/media/158295",
            "o:id": 158295
        },
        {
            "@id": "https://iiif.dl.itc.u-tokyo.ac.jp/repo/api/media/158296",
            "o:id": 158296
        },
        {
            "@id": "https://iiif.dl.itc.u-tokyo.ac.jp/repo/api/media/158297",
            "o:id": 158297
        },
        {
            "@id": "https://iiif.dl.itc.u-tokyo.ac.jp/repo/api/media/158298",
            "o:id": 158298
        },
        {
            "@id": "https://iiif.dl.itc.u-tokyo.ac.jp/repo/api/media/158299",
            "o:id": 158299
        },
        {
            "@id": "https://iiif.dl.itc.u-tokyo.ac.jp/repo/api/media/158300",
            "o:id": 158300
        },
        {
            "@id": "https://iiif.dl.itc.u-tokyo.ac.jp/repo/api/media/158301",
            "o:id": 158301
        },
        {
            "@id": "https://iiif.dl.itc.u-tokyo.ac.jp/repo/api/media/158302",
            "o:id": 158302
        },
        {
            "@id": "https://iiif.dl.itc.u-tokyo.ac.jp/repo/api/media/158303",
            "o:id": 158303
        },
        {
            "@id": "https://iiif.dl.itc.u-tokyo.ac.jp/repo/api/media/158304",
            "o:id": 158304
        },
        {
            "@id": "https://iiif.dl.itc.u-tokyo.ac.jp/repo/api/media/158305",
            "o:id": 158305
        },
        {
            "@id": "https://iiif.dl.itc.u-tokyo.ac.jp/repo/api/media/158306",
            "o:id": 158306
        },
        {
            "@id": "https://iiif.dl.itc.u-tokyo.ac.jp/repo/api/media/158307",
            "o:id": 158307
        },
        {
            "@id": "https://iiif.dl.itc.u-tokyo.ac.jp/repo/api/media/158308",
            "o:id": 158308
        },
        {
            "@id": "https://iiif.dl.itc.u-tokyo.ac.jp/repo/api/media/158309",
            "o:id": 158309
        },
        {
            "@id": "https://iiif.dl.itc.u-tokyo.ac.jp/repo/api/media/158310",
            "o:id": 158310
        },
        {
            "@id": "https://iiif.dl.itc.u-tokyo.ac.jp/repo/api/media/158311",
            "o:id": 158311
        },
        {
            "@id": "https://iiif.dl.itc.u-tokyo.ac.jp/repo/api/media/158312",
            "o:id": 158312
        },
        {
            "@id": "https://iiif.dl.itc.u-tokyo.ac.jp/repo/api/media/158313",
            "o:id": 158313
        },
        {
            "@id": "https://iiif.dl.itc.u-tokyo.ac.jp/repo/api/media/158314",
            "o:id": 158314
        },
        {
            "@id": "https://iiif.dl.itc.u-tokyo.ac.jp/repo/api/media/158315",
            "o:id": 158315
        },
        {
            "@id": "https://iiif.dl.itc.u-tokyo.ac.jp/repo/api/media/158316",
            "o:id": 158316
        },
        {
            "@id": "https://iiif.dl.itc.u-tokyo.ac.jp/repo/api/media/158317",
            "o:id": 158317
        },
        {
            "@id": "https://iiif.dl.itc.u-tokyo.ac.jp/repo/api/media/158318",
            "o:id": 158318
        },
        {
            "@id": "https://iiif.dl.itc.u-tokyo.ac.jp/repo/api/media/158319",
            "o:id": 158319
        },
        {
            "@id": "https://iiif.dl.itc.u-tokyo.ac.jp/repo/api/media/158320",
            "o:id": 158320
        },
        {
            "@id": "https://iiif.dl.itc.u-tokyo.ac.jp/repo/api/media/158321",
            "o:id": 158321
        },
        {
            "@id": "https://iiif.dl.itc.u-tokyo.ac.jp/repo/api/media/158322",
            "o:id": 158322
        },
        {
            "@id": "https://iiif.dl.itc.u-tokyo.ac.jp/repo/api/media/158323",
            "o:id": 158323
        },
        {
            "@id": "https://iiif.dl.itc.u-tokyo.ac.jp/repo/api/media/158324",
            "o:id": 158324
        },
        {
            "@id": "https://iiif.dl.itc.u-tokyo.ac.jp/repo/api/media/158325",
            "o:id": 158325
        },
        {
            "@id": "https://iiif.dl.itc.u-tokyo.ac.jp/repo/api/media/158326",
            "o:id": 158326
        },
        {
            "@id": "https://iiif.dl.itc.u-tokyo.ac.jp/repo/api/media/158327",
            "o:id": 158327
        },
        {
            "@id": "https://iiif.dl.itc.u-tokyo.ac.jp/repo/api/media/158328",
            "o:id": 158328
        },
        {
            "@id": "https://iiif.dl.itc.u-tokyo.ac.jp/repo/api/media/158329",
            "o:id": 158329
        },
        {
            "@id": "https://iiif.dl.itc.u-tokyo.ac.jp/repo/api/media/158330",
            "o:id": 158330
        },
        {
            "@id": "https://iiif.dl.itc.u-tokyo.ac.jp/repo/api/media/158331",
            "o:id": 158331
        },
        {
            "@id": "https://iiif.dl.itc.u-tokyo.ac.jp/repo/api/media/158332",
            "o:id": 158332
        },
        {
            "@id": "https://iiif.dl.itc.u-tokyo.ac.jp/repo/api/media/158333",
            "o:id": 158333
        },
        {
            "@id": "https://iiif.dl.itc.u-tokyo.ac.jp/repo/api/media/158334",
            "o:id": 158334
        },
        {
            "@id": "https://iiif.dl.itc.u-tokyo.ac.jp/repo/api/media/158335",
            "o:id": 158335
        },
        {
            "@id": "https://iiif.dl.itc.u-tokyo.ac.jp/repo/api/media/158336",
            "o:id": 158336
        },
        {
            "@id": "https://iiif.dl.itc.u-tokyo.ac.jp/repo/api/media/158337",
            "o:id": 158337
        },
        {
            "@id": "https://iiif.dl.itc.u-tokyo.ac.jp/repo/api/media/158338",
            "o:id": 158338
        },
        {
            "@id": "https://iiif.dl.itc.u-tokyo.ac.jp/repo/api/media/158339",
            "o:id": 158339
        },
        {
            "@id": "https://iiif.dl.itc.u-tokyo.ac.jp/repo/api/media/158340",
            "o:id": 158340
        },
        {
            "@id": "https://iiif.dl.itc.u-tokyo.ac.jp/repo/api/media/158341",
            "o:id": 158341
        },
        {
            "@id": "https://iiif.dl.itc.u-tokyo.ac.jp/repo/api/media/158342",
            "o:id": 158342
        },
        {
            "@id": "https://iiif.dl.itc.u-tokyo.ac.jp/repo/api/media/158343",
            "o:id": 158343
        },
        {
            "@id": "https://iiif.dl.itc.u-tokyo.ac.jp/repo/api/media/158344",
            "o:id": 158344
        },
        {
            "@id": "https://iiif.dl.itc.u-tokyo.ac.jp/repo/api/media/158345",
            "o:id": 158345
        },
        {
            "@id": "https://iiif.dl.itc.u-tokyo.ac.jp/repo/api/media/158346",
            "o:id": 158346
        },
        {
            "@id": "https://iiif.dl.itc.u-tokyo.ac.jp/repo/api/media/158347",
            "o:id": 158347
        },
        {
            "@id": "https://iiif.dl.itc.u-tokyo.ac.jp/repo/api/media/158348",
            "o:id": 158348
        },
        {
            "@id": "https://iiif.dl.itc.u-tokyo.ac.jp/repo/api/media/158349",
            "o:id": 158349
        },
        {
            "@id": "https://iiif.dl.itc.u-tokyo.ac.jp/repo/api/media/158350",
            "o:id": 158350
        },
        {
            "@id": "https://iiif.dl.itc.u-tokyo.ac.jp/repo/api/media/158351",
            "o:id": 158351
        },
        {
            "@id": "https://iiif.dl.itc.u-tokyo.ac.jp/repo/api/media/158352",
            "o:id": 158352
        },
        {
            "@id": "https://iiif.dl.itc.u-tokyo.ac.jp/repo/api/media/158353",
            "o:id": 158353
        },
        {
            "@id": "https://iiif.dl.itc.u-tokyo.ac.jp/repo/api/media/158354",
            "o:id": 158354
        },
        {
            "@id": "https://iiif.dl.itc.u-tokyo.ac.jp/repo/api/media/158355",
            "o:id": 158355
        },
        {
            "@id": "https://iiif.dl.itc.u-tokyo.ac.jp/repo/api/media/158356",
            "o:id": 158356
        },
        {
            "@id": "https://iiif.dl.itc.u-tokyo.ac.jp/repo/api/media/158357",
            "o:id": 158357
        },
        {
            "@id": "https://iiif.dl.itc.u-tokyo.ac.jp/repo/api/media/158358",
            "o:id": 158358
        },
        {
            "@id": "https://iiif.dl.itc.u-tokyo.ac.jp/repo/api/media/158359",
            "o:id": 158359
        }
    ],
    "o:modified": {
        "@type": "http://www.w3.org/2001/XMLSchema#dateTime",
        "@value": "2020-05-18T01:56:38+00:00"
    },
    "o:owner": {
        "@id": "https://iiif.dl.itc.u-tokyo.ac.jp/repo/api/users/1",
        "o:id": 1
    },
    "o:resource_class": {
        "@id": "https://iiif.dl.itc.u-tokyo.ac.jp/repo/api/resource_classes/26",
        "o:id": 26
    },
    "o:resource_template": {
        "@id": "https://iiif.dl.itc.u-tokyo.ac.jp/repo/api/resource_templates/7",
        "o:id": 7
    },
    "o:thumbnail": null,
    "rdfs:seeAlso": [
        {
            "@id": "https://iiif.dl.itc.u-tokyo.ac.jp/repo/api/items/25229",
            "is_public": true,
            "property_id": 282,
            "property_label": "seeAlso",
            "type": "uri"
        }
    ],
    "sc:attributionLabel": [
        {
            "@value": "東京大学総合図書館 General Library in the University of Tokyo, JAPAN",
            "is_public": true,
            "property_id": 190,
            "property_label": "attributionLabel",
            "type": "literal"
        }
    ],
    "sc:viewingDirection": [
        {
            "@id": "http://iiif.io/api/presentation/2#rightToLeftDirection",
            "is_public": true,
            "property_id": 198,
            "property_label": "viewingDirection",
            "type": "uri"
        }
    ],
    "uterms:databaseLabel": [
        {
            "@value": "田中芳男・博物学コレクション",
            "is_public": true,
            "property_id": 354,
            "property_label": "Database Label",
            "type": "literal"
        }
    ],
    "uterms:manifestUri": [
        {
            "@id": "https://iiif.dl.itc.u-tokyo.ac.jp/repo/iiif/2d522f09-a944-4348-afcc-69cf87e9dae4/manifest",
            "is_public": true,
            "property_id": 353,
            "property_label": "Manifest Uri",
            "type": "uri"
        }
    ],
    "uterms:sort": [
        {
            "@value": "00000039",
            "is_public": true,
            "property_id": 352,
            "property_label": "Sort",
            "type": "literal"
        }
    ]
}